MANIFEST.in
README.rst
setup.cfg
setup.py
docs/HISTORY.txt
docs/INSTALL.txt
docs/LICENSE.GPL
docs/LICENSE.txt
docs/diazo_parent-theme-model.png
docs/screenshot-desktop.jpg
docs/screenshot-desktop.png
docs/screenshot-mobile-landscape.jpg
docs/screenshot-mobile-landscape.png
docs/screenshot-mobile.png
docs/screenshot-tablet.png
htwkimn/__init__.py
htwkimn/__init__.pyc
htwkimn.theme.egg-info/PKG-INFO
htwkimn.theme.egg-info/SOURCES.txt
htwkimn.theme.egg-info/dependency_links.txt
htwkimn.theme.egg-info/entry_points.txt
htwkimn.theme.egg-info/namespace_packages.txt
htwkimn.theme.egg-info/not-zip-safe
htwkimn.theme.egg-info/paster_plugins.txt
htwkimn.theme.egg-info/requires.txt
htwkimn.theme.egg-info/top_level.txt
htwkimn/theme/__init__.py
htwkimn/theme/__init__.pyc
htwkimn/theme/configure.zcml
htwkimn/theme/tests.py
htwkimn/theme/profiles/default/actions.xml
htwkimn/theme/profiles/default/metadata.xml
htwkimn/theme/profiles/default/propertiestool.xml
htwkimn/theme/profiles/default/theme.xml
htwkimn/theme/profiles/default/tinymce.xml
htwkimn/theme/resources/index.html
htwkimn/theme/resources/manifest.cfg
htwkimn/theme/resources/preview.png
htwkimn/theme/resources/rules.xml
htwkimn/theme/resources/dummy-content/footer-portlets.src
htwkimn/theme/resources/dummy-content/quick-start-nav-icon1.jpg
htwkimn/theme/resources/dummy-content/quick-start-nav-icon2.jpg
htwkimn/theme/resources/dummy-content/quick-start-nav-icon4.jpg
htwkimn/theme/resources/dummy-content/quick-start-nav.src
htwkimn/theme/resources/images/favicon.ico
htwkimn/theme/resources/images/header-bg_lightgraphic.png
htwkimn/theme/resources/images/header-bg_lines-higher.png
htwkimn/theme/resources/images/header-bg_lines.png
htwkimn/theme/resources/images/header-bg_strong-lines.png
htwkimn/theme/resources/images/header-bg_strong-lines_higher.png
htwkimn/theme/resources/images/header-bg_strong.png
htwkimn/theme/resources/images/header-bg_weak.png
htwkimn/theme/resources/images/logo.png
htwkimn/theme/resources/images/logo_blue.png
htwkimn/theme/resources/sass/custom_theme-rules.scss
htwkimn/theme/resources/sass/overwrite_parent-css-rules.scss
htwkimn/theme/resources/sass/overwrite_parent-sass-rules.scss
htwkimn/theme/resources/sass/responsive.scss