Metadata-Version: 1.1
Name: htwkimn.theme
Version: 1.0.10
Summary: A responsive Diazo theme for mobile-friendly websites with Plone 4. As child theme, it extends the responsive plonetheme.onegov and aims for easy development with small or fast changing teams - like at the faculty IMN of the University of Applied Sience Leipzig (HTWK), Germany.
Home-page: https://github.com/lkosubek/htwkimn.theme
Author: Lars Kosubek
Author-email: post@larskosubek.com
License: GPL
Keywords: theme,responsive,diazo,plonetheme.onegov,university
Platform: UNKNOWN
Classifier: Framework :: Plone
Classifier: Programming Language :: Python
